<?xml version="1.0" encoding="UTF-8"?>
<!DOCTYPE mapper PUBLIC "-//mybatis.org//DTD Mapper 3.0//EN" "http://mybatis.org/dtd/mybatis-3-mapper.dtd">
<mapper namespace="com.airlenet.play.website.mapper.WechatMemberCardMapper">
    <resultMap id="BaseResultMap" type="com.airlenet.play.website.model.WechatMemberCard">
        <!--
          WARNING - @mbg.generated
          This element is automatically generated by MyBatis Generator, do not modify.
        -->
        <id column="id" jdbcType="BIGINT" property="id"/>
        <result column="createdDate" jdbcType="TIMESTAMP" property="createdDate"/>
        <result column="lastModifiedDate" jdbcType="TIMESTAMP" property="lastModifiedDate"/>
        <result column="cardId" jdbcType="VARCHAR" property="cardId"/>
        <result column="code" jdbcType="VARCHAR" property="code"/>
        <result column="membership_number" jdbcType="VARCHAR" property="membership_number"/>
        <result column="createdBy_id" jdbcType="BIGINT" property="createdBy_id"/>
        <result column="lastModifiedBy_id" jdbcType="BIGINT" property="lastModifiedBy_id"/>
        <result column="cardCoupon_id" jdbcType="BIGINT" property="cardCoupon_id"/>
        <result column="user_id" jdbcType="BIGINT" property="user_id"/>
    </resultMap>
    <sql id="Example_Where_Clause">
        <!--
          WARNING - @mbg.generated
          This element is automatically generated by MyBatis Generator, do not modify.
        -->
        <where>
            <foreach collection="oredCriteria" item="criteria" separator="or">
                <if test="criteria.valid">
                    <trim prefix="(" prefixOverrides="and" suffix=")">
                        <foreach collection="criteria.criteria" item="criterion">
                            <choose>
                                <when test="criterion.noValue">
                                    and ${criterion.condition}
                                </when>
                                <when test="criterion.singleValue">
                                    and ${criterion.condition} #{criterion.value}
                                </when>
                                <when test="criterion.betweenValue">
                                    and ${criterion.condition} #{criterion.value} and #{criterion.secondValue}
                                </when>
                                <when test="criterion.listValue">
                                    and ${criterion.condition}
                                    <foreach close=")" collection="criterion.value" item="listItem" open="("
                                             separator=",">
                                        #{listItem}
                                    </foreach>
                                </when>
                            </choose>
                        </foreach>
                    </trim>
                </if>
            </foreach>
        </where>
    </sql>
    <sql id="Update_By_Example_Where_Clause">
        <!--
          WARNING - @mbg.generated
          This element is automatically generated by MyBatis Generator, do not modify.
        -->
        <where>
            <foreach collection="example.oredCriteria" item="criteria" separator="or">
                <if test="criteria.valid">
                    <trim prefix="(" prefixOverrides="and" suffix=")">
                        <foreach collection="criteria.criteria" item="criterion">
                            <choose>
                                <when test="criterion.noValue">
                                    and ${criterion.condition}
                                </when>
                                <when test="criterion.singleValue">
                                    and ${criterion.condition} #{criterion.value}
                                </when>
                                <when test="criterion.betweenValue">
                                    and ${criterion.condition} #{criterion.value} and #{criterion.secondValue}
                                </when>
                                <when test="criterion.listValue">
                                    and ${criterion.condition}
                                    <foreach close=")" collection="criterion.value" item="listItem" open="("
                                             separator=",">
                                        #{listItem}
                                    </foreach>
                                </when>
                            </choose>
                        </foreach>
                    </trim>
                </if>
            </foreach>
        </where>
    </sql>
    <sql id="Base_Column_List">
        <!--
          WARNING - @mbg.generated
          This element is automatically generated by MyBatis Generator, do not modify.
        -->
        id, createdDate, lastModifiedDate, cardId, code, membership_number, createdBy_id,
        lastModifiedBy_id, cardCoupon_id, user_id
    </sql>
    <select id="selectByExample" parameterType="com.airlenet.play.website.model.WechatMemberCardExample"
            resultMap="BaseResultMap">
        <!--
          WARNING - @mbg.generated
          This element is automatically generated by MyBatis Generator, do not modify.
        -->
        select
        <if test="distinct">
            distinct
        </if>
        <include refid="Base_Column_List"/>
        from wechat_member_card
        <if test="_parameter != null">
            <include refid="Example_Where_Clause"/>
        </if>
        <if test="orderByClause != null">
            order by ${orderByClause}
        </if>
        <if test="limit != null">
            <if test="offset != null">
                limit ${offset}, ${limit}
            </if>
            <if test="offset == null">
                limit ${limit}
            </if>
        </if>
    </select>
    <select id="selectByPrimaryKey" parameterType="java.lang.Long" resultMap="BaseResultMap">
        <!--
          WARNING - @mbg.generated
          This element is automatically generated by MyBatis Generator, do not modify.
        -->
        select
        <include refid="Base_Column_List"/>
        from wechat_member_card
        where id = #{id,jdbcType=BIGINT}
    </select>
    <delete id="deleteByPrimaryKey" parameterType="java.lang.Long">
        <!--
          WARNING - @mbg.generated
          This element is automatically generated by MyBatis Generator, do not modify.
        -->
        delete from wechat_member_card
        where id = #{id,jdbcType=BIGINT}
    </delete>
    <delete id="deleteByExample" parameterType="com.airlenet.play.website.model.WechatMemberCardExample">
        <!--
          WARNING - @mbg.generated
          This element is automatically generated by MyBatis Generator, do not modify.
        -->
        delete from wechat_member_card
        <if test="_parameter != null">
            <include refid="Example_Where_Clause"/>
        </if>
    </delete>
    <insert id="insert" parameterType="com.airlenet.play.website.model.WechatMemberCard">
        <!--
          WARNING - @mbg.generated
          This element is automatically generated by MyBatis Generator, do not modify.
        -->
        <selectKey keyProperty="id" order="AFTER" resultType="java.lang.Long">
            SELECT LAST_INSERT_ID()
        </selectKey>
        insert into wechat_member_card (createdDate, lastModifiedDate,
        cardId, code, membership_number,
        createdBy_id, lastModifiedBy_id, cardCoupon_id,
        user_id)
        values (#{createdDate,jdbcType=TIMESTAMP}, #{lastModifiedDate,jdbcType=TIMESTAMP},
        #{cardId,jdbcType=VARCHAR}, #{code,jdbcType=VARCHAR}, #{membership_number,jdbcType=VARCHAR},
        #{createdBy_id,jdbcType=BIGINT}, #{lastModifiedBy_id,jdbcType=BIGINT}, #{cardCoupon_id,jdbcType=BIGINT},
        #{user_id,jdbcType=BIGINT})
    </insert>
    <insert id="insertSelective" parameterType="com.airlenet.play.website.model.WechatMemberCard">
        <!--
          WARNING - @mbg.generated
          This element is automatically generated by MyBatis Generator, do not modify.
        -->
        <selectKey keyProperty="id" order="AFTER" resultType="java.lang.Long">
            SELECT LAST_INSERT_ID()
        </selectKey>
        insert into wechat_member_card
        <trim prefix="(" suffix=")" suffixOverrides=",">
            <if test="createdDate != null">
                createdDate,
            </if>
            <if test="lastModifiedDate != null">
                lastModifiedDate,
            </if>
            <if test="cardId != null">
                cardId,
            </if>
            <if test="code != null">
                code,
            </if>
            <if test="membership_number != null">
                membership_number,
            </if>
            <if test="createdBy_id != null">
                createdBy_id,
            </if>
            <if test="lastModifiedBy_id != null">
                lastModifiedBy_id,
            </if>
            <if test="cardCoupon_id != null">
                cardCoupon_id,
            </if>
            <if test="user_id != null">
                user_id,
            </if>
        </trim>
        <trim prefix="values (" suffix=")" suffixOverrides=",">
            <if test="createdDate != null">
                #{createdDate,jdbcType=TIMESTAMP},
            </if>
            <if test="lastModifiedDate != null">
                #{lastModifiedDate,jdbcType=TIMESTAMP},
            </if>
            <if test="cardId != null">
                #{cardId,jdbcType=VARCHAR},
            </if>
            <if test="code != null">
                #{code,jdbcType=VARCHAR},
            </if>
            <if test="membership_number != null">
                #{membership_number,jdbcType=VARCHAR},
            </if>
            <if test="createdBy_id != null">
                #{createdBy_id,jdbcType=BIGINT},
            </if>
            <if test="lastModifiedBy_id != null">
                #{lastModifiedBy_id,jdbcType=BIGINT},
            </if>
            <if test="cardCoupon_id != null">
                #{cardCoupon_id,jdbcType=BIGINT},
            </if>
            <if test="user_id != null">
                #{user_id,jdbcType=BIGINT},
            </if>
        </trim>
    </insert>
    <select id="countByExample" parameterType="com.airlenet.play.website.model.WechatMemberCardExample"
            resultType="java.lang.Long">
        <!--
          WARNING - @mbg.generated
          This element is automatically generated by MyBatis Generator, do not modify.
        -->
        select count(*) from wechat_member_card
        <if test="_parameter != null">
            <include refid="Example_Where_Clause"/>
        </if>
    </select>
    <update id="updateByExampleSelective" parameterType="map">
        <!--
          WARNING - @mbg.generated
          This element is automatically generated by MyBatis Generator, do not modify.
        -->
        update wechat_member_card
        <set>
            <if test="record.id != null">
                id = #{record.id,jdbcType=BIGINT},
            </if>
            <if test="record.createdDate != null">
                createdDate = #{record.createdDate,jdbcType=TIMESTAMP},
            </if>
            <if test="record.lastModifiedDate != null">
                lastModifiedDate = #{record.lastModifiedDate,jdbcType=TIMESTAMP},
            </if>
            <if test="record.cardId != null">
                cardId = #{record.cardId,jdbcType=VARCHAR},
            </if>
            <if test="record.code != null">
                code = #{record.code,jdbcType=VARCHAR},
            </if>
            <if test="record.membership_number != null">
                membership_number = #{record.membership_number,jdbcType=VARCHAR},
            </if>
            <if test="record.createdBy_id != null">
                createdBy_id = #{record.createdBy_id,jdbcType=BIGINT},
            </if>
            <if test="record.lastModifiedBy_id != null">
                lastModifiedBy_id = #{record.lastModifiedBy_id,jdbcType=BIGINT},
            </if>
            <if test="record.cardCoupon_id != null">
                cardCoupon_id = #{record.cardCoupon_id,jdbcType=BIGINT},
            </if>
            <if test="record.user_id != null">
                user_id = #{record.user_id,jdbcType=BIGINT},
            </if>
        </set>
        <if test="_parameter != null">
            <include refid="Update_By_Example_Where_Clause"/>
        </if>
    </update>
    <update id="updateByExample" parameterType="map">
        <!--
          WARNING - @mbg.generated
          This element is automatically generated by MyBatis Generator, do not modify.
        -->
        update wechat_member_card
        set id = #{record.id,jdbcType=BIGINT},
        createdDate = #{record.createdDate,jdbcType=TIMESTAMP},
        lastModifiedDate = #{record.lastModifiedDate,jdbcType=TIMESTAMP},
        cardId = #{record.cardId,jdbcType=VARCHAR},
        code = #{record.code,jdbcType=VARCHAR},
        membership_number = #{record.membership_number,jdbcType=VARCHAR},
        createdBy_id = #{record.createdBy_id,jdbcType=BIGINT},
        lastModifiedBy_id = #{record.lastModifiedBy_id,jdbcType=BIGINT},
        cardCoupon_id = #{record.cardCoupon_id,jdbcType=BIGINT},
        user_id = #{record.user_id,jdbcType=BIGINT}
        <if test="_parameter != null">
            <include refid="Update_By_Example_Where_Clause"/>
        </if>
    </update>
    <update id="updateByPrimaryKeySelective" parameterType="com.airlenet.play.website.model.WechatMemberCard">
        <!--
          WARNING - @mbg.generated
          This element is automatically generated by MyBatis Generator, do not modify.
        -->
        update wechat_member_card
        <set>
            <if test="createdDate != null">
                createdDate = #{createdDate,jdbcType=TIMESTAMP},
            </if>
            <if test="lastModifiedDate != null">
                lastModifiedDate = #{lastModifiedDate,jdbcType=TIMESTAMP},
            </if>
            <if test="cardId != null">
                cardId = #{cardId,jdbcType=VARCHAR},
            </if>
            <if test="code != null">
                code = #{code,jdbcType=VARCHAR},
            </if>
            <if test="membership_number != null">
                membership_number = #{membership_number,jdbcType=VARCHAR},
            </if>
            <if test="createdBy_id != null">
                createdBy_id = #{createdBy_id,jdbcType=BIGINT},
            </if>
            <if test="lastModifiedBy_id != null">
                lastModifiedBy_id = #{lastModifiedBy_id,jdbcType=BIGINT},
            </if>
            <if test="cardCoupon_id != null">
                cardCoupon_id = #{cardCoupon_id,jdbcType=BIGINT},
            </if>
            <if test="user_id != null">
                user_id = #{user_id,jdbcType=BIGINT},
            </if>
        </set>
        where id = #{id,jdbcType=BIGINT}
    </update>
    <update id="updateByPrimaryKey" parameterType="com.airlenet.play.website.model.WechatMemberCard">
        <!--
          WARNING - @mbg.generated
          This element is automatically generated by MyBatis Generator, do not modify.
        -->
        update wechat_member_card
        set createdDate = #{createdDate,jdbcType=TIMESTAMP},
        lastModifiedDate = #{lastModifiedDate,jdbcType=TIMESTAMP},
        cardId = #{cardId,jdbcType=VARCHAR},
        code = #{code,jdbcType=VARCHAR},
        membership_number = #{membership_number,jdbcType=VARCHAR},
        createdBy_id = #{createdBy_id,jdbcType=BIGINT},
        lastModifiedBy_id = #{lastModifiedBy_id,jdbcType=BIGINT},
        cardCoupon_id = #{cardCoupon_id,jdbcType=BIGINT},
        user_id = #{user_id,jdbcType=BIGINT}
        where id = #{id,jdbcType=BIGINT}
    </update>
</mapper>